{"buildTime":"2024-01-19T17:46:35.546Z","sources":[{"id":"MangaTube","name":"MangaTube","author":"NmN","desc":"Extension that pulls manga from MangaTube.","website":"http://github.com/pandeynmm","contentRating":"EVERYONE","version":"3.0.0","icon":"icon.png","tags":[{"text":"GERMAN","type":"info"}],"websiteBaseURL":"https://manga-tube.me/","intents":5},{"id":"MangaWorld","name":"MangaWorld","author":"NmN","desc":"Extension that pulls manga from MangaWorld (0.8).","website":"http://github.com/pandeynmm","contentRating":"EVERYONE","version":"3.0.0","icon":"icon.png","tags":[{"text":"ITALIAN","type":"info"}],"websiteBaseURL":"https://www.mangaworld.bz","intents":5}],"builtWith":{"toolchain":"0.8.0-alpha.47","types":"0.8.0-alpha.47"}}